grep_mcp/__init__.py
grep_mcp/__main__.py
grep_mcp/server.py
grep_mcp-1.0.3.dist-info/METADATA
grep_mcp-1.0.3.dist-info/WHEEL
grep_mcp-1.0.3.dist-info/entry_points.txt
grep_mcp-1.0.3.dist-info/licenses/LICENSE
grep_mcp-1.0.3.dist-info/RECORD
