Metadata-Version: 2.4
Name: grep-mcp
Version: 1.0.3
Summary: Grep MCP Server - File content and filename search for AI assistants
Project-URL: Homepage, https://github.com/galperetz/grep-mcp
Project-URL: Repository, https://github.com/galperetz/grep-mcp
Project-URL: Issues, https://github.com/galperetz/grep-mcp/issues
Author-email: Gal Peretz <gal@galperetz.com>
License: MIT
License-File: LICENSE
Keywords: ai-assistant,file-search,grep,mcp,pattern-matching,search
Classifier: Development Status :: 5 - Production/Stable
Classifier: Intended Audience :: Developers
Classifier: License :: OSI Approved :: MIT License
Classifier: Programming Language :: Python :: 3
Classifier: Programming Language :: Python :: 3.10
Classifier: Programming Language :: Python :: 3.11
Classifier: Programming Language :: Python :: 3.12
Classifier: Topic :: Communications :: Chat
Classifier: Topic :: Desktop Environment :: File Managers
Classifier: Topic :: Software Development :: Libraries :: Python Modules
Requires-Python: >=3.10
Requires-Dist: aiohttp
Requires-Dist: mcp
Requires-Dist: starlette
Requires-Dist: uvicorn
Provides-Extra: dev
Requires-Dist: black>=22.0.0; extra == 'dev'
Requires-Dist: isort>=5.0.0; extra == 'dev'
Requires-Dist: mypy>=1.0.0; extra == 'dev'
Requires-Dist: pytest>=7.0.0; extra == 'dev'
